package_controller/__init__.py
package_controller/cli/__init__.py
package_controller/cli/main.py
package_controller/cli/commands/__init__.py
package_controller/cli/commands/add.py
package_controller/cli/commands/build.py
package_controller/cli/commands/bump.py
package_controller/cli/commands/commit.py
package_controller/cli/commands/diff.py
package_controller/cli/commands/document.py
package_controller/cli/commands/init.py
package_controller/cli/commands/pin.py
package_controller/cli/commands/publish.py
package_controller/cli/commands/release.py
package_controller/cli/commands/resave.py
package_controller/cli/commands/save.py
package_controller/cli/commands/test.py
package_controller/cli/commands/undo.py
package_controller/cli/commands/unpin.py
package_controller/cli/commands/unsave.py
package_controller/cli/commands/version.py
package_controller/library/__init__.py
package_controller/library/commands/__init__.py
package_controller/library/commands/build.py
package_controller/library/commands/bump.py
package_controller/library/commands/document.py
package_controller/library/commands/init.py
package_controller/library/commands/pin.py
package_controller/library/commands/publish.py
package_controller/library/commands/release.py
package_controller/library/commands/resave.py
package_controller/library/commands/test.py
package_controller/library/commands/undo.py
package_controller/library/commands/unpin.py
package_controller/library/commands/unsave.py
package_controller/library/commands/version.py
package_controller/library/fascades/__init__.py
package_controller/library/fascades/build_package.py
package_controller/library/fascades/bump_version.py
package_controller/library/fascades/get_version.py
package_controller/library/fascades/pin_versions.py
package_controller/library/fascades/release_package.py
package_controller/library/fascades/test_package.py
package_controller/library/fascades/unpin_versions.py
package_controller/library/fascades/update_documentation.py
package_controller-3.2.1.dist-info/LICENSE.txt
package_controller-3.2.1.dist-info/METADATA
package_controller-3.2.1.dist-info/WHEEL
package_controller-3.2.1.dist-info/entry_points.txt
package_controller-3.2.1.dist-info/top_level.txt
package_controller-3.2.1.dist-info/RECORD
