Metadata-Version: 2.1
Name: package-controller
Version: 3.2.1
Summary: A CLI tool that acts as a wrapper for various other programs to make updating and publishing python and node packages easier
Home-page: https://www.alexseitsinger.com/packages/python/package-controller
Author: Alex Seitsinger
Author-email: software@alexseitsinger.com
License: BSD 2-Clause License
Project-URL: Documentation, https://www.alexseitsinger.com/packages/python/package-controller
Project-URL: Source, https://github.com/alexseitsinger/package-controller
Project-URL: Tracker, https://github.com/alexseitsinger/package-controller/issues
Keywords: package,semantic version,git,distribution
Platform: UNKNOWN
Classifier: Development Status :: 5 - Production/Stable
Classifier: License :: OSI Approved :: BSD License
Classifier: Programming Language :: Python :: 2
Classifier: Programming Language :: Python :: 3
Classifier: Environment :: Console
Classifier: Intended Audience :: Developers
Classifier: Topic :: Documentation
Classifier: Topic :: Software Development :: Build Tools
Classifier: Topic :: Software Development :: Documentation
Classifier: Topic :: Software Development :: Version Control :: Git
Classifier: Topic :: System :: Archiving :: Packaging
Classifier: Topic :: System :: Software Distribution
Classifier: Topic :: Utilities
Classifier: Natural Language :: English
Classifier: Operating System :: OS Independent
Requires-Dist: click
Requires-Dist: semver
Requires-Dist: toml
Requires-Dist: requests
